LICENSE
MANIFEST.in
README.md
setup.py
validate_version_code/__init__.py
validate_version_code/__version__.py
validate_version_code/validate_version_code.py
validate_version_code.egg-info/PKG-INFO
validate_version_code.egg-info/SOURCES.txt
validate_version_code.egg-info/dependency_links.txt
validate_version_code.egg-info/requires.txt
validate_version_code.egg-info/top_level.txt