Metadata-Version: 2.1
Name: validate-version-code
Version: 1.0.5
Summary: Python package to validate version codes.
Home-page: https://github.com/LucaCappelletti94/validate_version_code
Author: Luca Cappelletti
Author-email: cappelletti.luca94@gmail.com
License: MIT
Platform: UNKNOWN
Classifier: Development Status :: 5 - Production/Stable
Classifier: License :: OSI Approved :: MIT License
Classifier: Programming Language :: Python :: 3
Provides-Extra: test
License-File: LICENSE
